[
    {
        "parkrunning": 92,
        "junior parkrunning": 0,
        "5k Cancellations": 8,
        "junior Cancellations": 0,
        "Total": 100,
        "time": "2022-04-24 21:10:17.359774"
    },
    {
        "parkrunning": 97,
        "5k Cancellations": 3,
        "Total": 100,
        "time": "2022-04-25 01:19:49.962120"
    },
    {
        "parkrunning": 97,
        "junior parkrunning": 0,
        "5k Cancellations": 3,
        "junior Cancellations": 0,
        "Total": 100,
        "time": "2022-04-26 06:21:18.226518"
    }
]
