[
    {
        "parkrunning": 102,
        "junior parkrunning": 1,
        "5k Cancellations": 11,
        "junior Cancellations": 2,
        "Total": 116,
        "time": "2022-03-27 21:10:35.515330"
    },
    {
        "parkrunning": 107,
        "junior parkrunning": 2,
        "5k Cancellations": 6,
        "junior Cancellations": 1,
        "Total": 116,
        "time": "2022-03-28 01:19:38.150002"
    },
    {
        "parkrunning": 107,
        "5k Cancellations": 6,
        "Total": 116,
        "time": "2022-03-28 21:14:53.475856"
    },
    {
        "parkrunning": 106,
        "5k Cancellations": 7,
        "Total": 116,
        "time": "2022-03-29 01:12:37.058668"
    },
    {
        "parkrunning": 106,
        "5k Cancellations": 7,
        "Total": 116,
        "time": "2022-03-29 09:16:11.223717"
    },
    {
        "parkrunning": 104,
        "5k Cancellations": 9,
        "Total": 116,
        "time": "2022-03-29 12:30:57.932317"
    },
    {
        "parkrunning": 104,
        "junior parkrunning": 2,
        "5k Cancellations": 9,
        "junior Cancellations": 1,
        "Total": 116,
        "time": "2022-03-29 18:19:59.567310"
    }
]
