[
    {
        "parkrunning": 121,
        "junior parkrunning": 2,
        "5k Cancellations": 2,
        "junior Cancellations": 0,
        "Total": 125,
        "time": "2024-03-17 21:10:36.440849"
    },
    {
        "junior parkrunning": 1,
        "junior Cancellations": 1,
        "Total": 125,
        "time": "2024-03-18 01:00:28.900025"
    },
    {
        "parkrunning": 121,
        "junior parkrunning": 1,
        "5k Cancellations": 2,
        "junior Cancellations": 1,
        "Total": 125,
        "time": "2024-03-18 09:14:11.043995"
    }
]
