[
    {
        "parkrunning": 117,
        "junior parkrunning": 2,
        "5k Cancellations": 2,
        "junior Cancellations": 0,
        "Total": 121,
        "time": "2023-04-16 21:08:24.255114"
    },
    {
        "parkrunning": 119,
        "5k Cancellations": 0,
        "Total": 121,
        "time": "2023-04-17 01:09:53.783183"
    },
    {
        "parkrunning": 119,
        "5k Cancellations": 0,
        "Total": 121,
        "time": "2023-04-18 12:27:49.399693"
    },
    {
        "parkrunning": 118,
        "5k Cancellations": 1,
        "Total": 121,
        "time": "2023-04-18 15:16:22.745759"
    },
    {
        "parkrunning": 118,
        "5k Cancellations": 1,
        "Total": 121,
        "time": "2023-04-20 03:14:49.670523"
    },
    {
        "parkrunning": 116,
        "5k Cancellations": 3,
        "Total": 121,
        "time": "2023-04-20 06:18:25.465818"
    },
    {
        "parkrunning": 115,
        "5k Cancellations": 4,
        "Total": 121,
        "time": "2023-04-20 09:14:00.896016"
    },
    {
        "parkrunning": 115,
        "5k Cancellations": 4,
        "Total": 121,
        "time": "2023-04-20 12:27:18.556305"
    },
    {
        "parkrunning": 114,
        "5k Cancellations": 5,
        "Total": 121,
        "time": "2023-04-20 15:14:19.676672"
    },
    {
        "parkrunning": 114,
        "5k Cancellations": 5,
        "Total": 121,
        "time": "2023-04-20 21:12:09.458159"
    },
    {
        "parkrunning": 113,
        "5k Cancellations": 6,
        "Total": 121,
        "time": "2023-04-21 01:24:17.507517"
    },
    {
        "parkrunning": 113,
        "junior parkrunning": 2,
        "5k Cancellations": 6,
        "junior Cancellations": 0,
        "Total": 121,
        "time": "2023-04-22 06:16:30.285099"
    }
]
