[
    {
        "parkrunning": 132,
        "junior parkrunning": 2,
        "5k Cancellations": 4,
        "junior Cancellations": 0,
        "Total": 138,
        "time": "2025-12-28 18:22:15.965857"
    },
    {
        "parkrunning": 135,
        "5k Cancellations": 1,
        "Total": 138,
        "time": "2025-12-29 01:54:03.778706"
    },
    {
        "parkrunning": 135,
        "5k Cancellations": 1,
        "Total": 138,
        "time": "2025-12-31 06:35:11.668763"
    },
    {
        "parkrunning": 134,
        "5k Cancellations": 2,
        "Total": 138,
        "time": "2026-01-01 15:22:58.091444"
    },
    {
        "parkrunning": 134,
        "5k Cancellations": 2,
        "Total": 138,
        "time": "2026-01-01 18:31:38.583459"
    },
    {
        "parkrunning": 133,
        "5k Cancellations": 3,
        "Total": 138,
        "time": "2026-01-02 22:27:42.241898"
    },
    {
        "parkrunning": 133,
        "5k Cancellations": 3,
        "Total": 138,
        "time": "2026-01-04 12:30:21.386427"
    },
    {
        "parkrunning": 136,
        "5k Cancellations": 0,
        "Total": 138,
        "time": "2026-01-05 06:40:07.014082"
    },
    {
        "parkrunning": 136,
        "5k Cancellations": 0,
        "Total": 138,
        "time": "2026-01-07 01:47:40.964592"
    },
    {
        "parkrunning": 134,
        "5k Cancellations": 2,
        "Total": 138,
        "time": "2026-01-07 18:34:50.923241"
    },
    {
        "parkrunning": 134,
        "5k Cancellations": 2,
        "Total": 138,
        "time": "2026-01-08 18:30:10.313286"
    },
    {
        "parkrunning": 129,
        "5k Cancellations": 7,
        "Total": 138,
        "time": "2026-01-09 21:27:46.975481"
    },
    {
        "parkrunning": 128,
        "5k Cancellations": 8,
        "Total": 138,
        "time": "2026-01-10 03:24:14.608741"
    },
    {
        "parkrunning": 128,
        "5k Cancellations": 8,
        "Total": 138,
        "time": "2026-01-11 21:14:18.413367"
    },
    {
        "parkrunning": 134,
        "5k Cancellations": 2,
        "Total": 138,
        "time": "2026-01-12 04:10:51.583600"
    },
    {
        "parkrunning": 134,
        "5k Cancellations": 2,
        "Total": 138,
        "time": "2026-01-13 15:26:43.338118"
    },
    {
        "parkrunning": 133,
        "5k Cancellations": 3,
        "Total": 138,
        "time": "2026-01-14 09:29:36.487434"
    },
    {
        "parkrunning": 133,
        "5k Cancellations": 3,
        "Total": 138,
        "time": "2026-01-14 18:35:23.649919"
    },
    {
        "parkrunning": 132,
        "5k Cancellations": 4,
        "Total": 138,
        "time": "2026-01-15 18:37:56.164061"
    },
    {
        "parkrunning": 132,
        "junior parkrunning": 2,
        "5k Cancellations": 4,
        "junior Cancellations": 0,
        "Total": 138,
        "time": "2026-01-16 04:05:39.016808"
    }
]
