[
    {
        "parkrunning": 117,
        "junior parkrunning": 1,
        "5k Cancellations": 2,
        "junior Cancellations": 1,
        "Total": 121,
        "time": "2023-05-14 21:09:05.777966"
    },
    {
        "parkrunning": 119,
        "junior parkrunning": 2,
        "5k Cancellations": 0,
        "junior Cancellations": 0,
        "Total": 121,
        "time": "2023-05-15 01:11:36.665054"
    },
    {
        "parkrunning": 119,
        "junior parkrunning": 2,
        "5k Cancellations": 0,
        "junior Cancellations": 0,
        "Total": 121,
        "time": "2023-05-16 06:17:57.251553"
    }
]
