[
    {
        "parkrunning": 48,
        "junior parkrunning": 0,
        "5k Cancellations": 1,
        "junior Cancellations": 1,
        "Total": 50,
        "time": "2023-05-07 21:09:06.182882"
    },
    {
        "junior parkrunning": 1,
        "junior Cancellations": 0,
        "Total": 50,
        "time": "2023-05-08 01:07:08.613102"
    },
    {
        "5k Cancellations": 1,
        "Total": 50,
        "time": "2023-05-09 21:12:23.608662"
    },
    {
        "5k Cancellations": 0,
        "Total": 49,
        "time": "2023-05-10 01:08:24.444131"
    },
    {
        "5k Cancellations": 0,
        "Total": 49,
        "time": "2023-05-10 03:14:27.164109"
    },
    {
        "5k Cancellations": 1,
        "Total": 50,
        "time": "2023-05-10 06:17:36.596944"
    },
    {
        "5k Cancellations": 0,
        "Total": 49,
        "time": "2023-05-10 09:14:02.161082"
    },
    {
        "parkrunning": 48,
        "junior parkrunning": 1,
        "5k Cancellations": 0,
        "junior Cancellations": 0,
        "Total": 49,
        "time": "2023-05-13 08:35:30.946166"
    }
]
