[
    {
        "parkrunning": 20,
        "junior parkrunning": 0,
        "5k Cancellations": 1,
        "junior Cancellations": 0,
        "Total": 21,
        "time": "2023-10-01 21:08:29.354043"
    },
    {
        "parkrunning": 21,
        "5k Cancellations": 0,
        "Total": 21,
        "time": "2023-10-02 01:00:10.474163"
    },
    {
        "parkrunning": 21,
        "junior parkrunning": 0,
        "5k Cancellations": 0,
        "junior Cancellations": 0,
        "Total": 21,
        "time": "2023-10-02 12:26:48.668427"
    }
]
