[
    {
        "parkrunning": 93,
        "junior parkrunning": 2,
        "5k Cancellations": 2,
        "junior Cancellations": 0,
        "Total": 97,
        "time": "2022-02-13 21:08:45.607955"
    },
    {
        "parkrunning": 95,
        "5k Cancellations": 0,
        "Total": 97,
        "time": "2022-02-14 00:53:31.611665"
    },
    {
        "parkrunning": 95,
        "junior parkrunning": 2,
        "5k Cancellations": 0,
        "junior Cancellations": 0,
        "Total": 97,
        "time": "2022-02-15 21:12:45.223395"
    }
]
