[
    {
        "parkrunning": 109,
        "junior parkrunning": 2,
        "5k Cancellations": 2,
        "junior Cancellations": 0,
        "Total": 113,
        "time": "2024-07-14 21:10:17.421590"
    },
    {
        "parkrunning": 110,
        "5k Cancellations": 1,
        "Total": 113,
        "time": "2024-07-15 01:10:57.537962"
    },
    {
        "parkrunning": 110,
        "5k Cancellations": 1,
        "Total": 113,
        "time": "2024-07-19 09:20:29.108621"
    },
    {
        "parkrunning": 109,
        "5k Cancellations": 2,
        "Total": 113,
        "time": "2024-07-19 12:36:47.614117"
    },
    {
        "parkrunning": 109,
        "5k Cancellations": 2,
        "Total": 113,
        "time": "2024-07-19 19:16:45.734607"
    },
    {
        "parkrunning": 108,
        "5k Cancellations": 3,
        "Total": 113,
        "time": "2024-07-19 20:21:52.713088"
    },
    {
        "parkrunning": 108,
        "5k Cancellations": 3,
        "Total": 113,
        "time": "2024-07-19 22:19:44.845567"
    },
    {
        "parkrunning": 105,
        "5k Cancellations": 6,
        "Total": 113,
        "time": "2024-07-19 23:19:20.703711"
    },
    {
        "parkrunning": 105,
        "junior parkrunning": 2,
        "5k Cancellations": 6,
        "junior Cancellations": 0,
        "Total": 113,
        "time": "2024-07-20 08:36:08.195905"
    }
]
