[
    {
        "parkrunning": 94,
        "junior parkrunning": 2,
        "5k Cancellations": 7,
        "junior Cancellations": 0,
        "Total": 103,
        "time": "2022-10-02 21:12:37.867587"
    },
    {
        "parkrunning": 101,
        "5k Cancellations": 0,
        "Total": 103,
        "time": "2022-10-03 01:46:26.859143"
    },
    {
        "parkrunning": 101,
        "junior parkrunning": 2,
        "5k Cancellations": 0,
        "junior Cancellations": 0,
        "Total": 103,
        "time": "2022-10-04 04:08:33.485060"
    }
]
