[
    {
        "parkrunning": 1,
        "junior parkrunning": 0,
        "5k Cancellations": 1,
        "junior Cancellations": 0,
        "Total": 2,
        "time": "2026-01-25 18:22:43.467081"
    },
    {
        "parkrunning": 1,
        "5k Cancellations": 1,
        "Total": 2,
        "time": "2026-02-09 10:03:25.269272"
    },
    {
        "parkrunning": 2,
        "5k Cancellations": 0,
        "Total": 2,
        "time": "2026-02-09 23:04:46.354726"
    },
    {
        "parkrunning": 2,
        "5k Cancellations": 0,
        "Total": 2,
        "time": "2026-02-10 07:05:28.618752"
    },
    {
        "parkrunning": 1,
        "5k Cancellations": 1,
        "Total": 2,
        "time": "2026-02-10 10:01:06.778984"
    },
    {
        "parkrunning": 2,
        "5k Cancellations": 0,
        "Total": 2,
        "time": "2026-02-10 13:15:41.218576"
    },
    {
        "parkrunning": 2,
        "5k Cancellations": 0,
        "Total": 2,
        "time": "2026-02-10 16:06:36.880298"
    },
    {
        "parkrunning": 1,
        "5k Cancellations": 1,
        "Total": 2,
        "time": "2026-02-10 19:05:34.546351"
    },
    {
        "parkrunning": 1,
        "5k Cancellations": 1,
        "Total": 2,
        "time": "2026-02-10 21:42:14.592481"
    },
    {
        "parkrunning": 2,
        "5k Cancellations": 0,
        "Total": 2,
        "time": "2026-02-11 02:27:55.727783"
    },
    {
        "parkrunning": 2,
        "5k Cancellations": 0,
        "Total": 2,
        "time": "2026-02-11 07:02:16.100962"
    },
    {
        "parkrunning": 1,
        "5k Cancellations": 1,
        "Total": 2,
        "time": "2026-02-11 09:54:29.612384"
    },
    {
        "parkrunning": 1,
        "5k Cancellations": 1,
        "Total": 2,
        "time": "2026-02-11 16:02:47.469997"
    },
    {
        "parkrunning": 2,
        "5k Cancellations": 0,
        "Total": 2,
        "time": "2026-02-11 19:04:31.539935"
    },
    {
        "parkrunning": 1,
        "5k Cancellations": 1,
        "Total": 2,
        "time": "2026-02-11 21:34:20.208776"
    },
    {
        "parkrunning": 2,
        "5k Cancellations": 0,
        "Total": 2,
        "time": "2026-02-12 02:23:06.696414"
    },
    {
        "parkrunning": 2,
        "5k Cancellations": 0,
        "Total": 2,
        "time": "2026-02-12 04:58:33.424890"
    },
    {
        "parkrunning": 1,
        "5k Cancellations": 1,
        "Total": 2,
        "time": "2026-02-12 07:02:10.795381"
    },
    {
        "parkrunning": 1,
        "5k Cancellations": 1,
        "Total": 2,
        "time": "2026-02-12 09:51:48.703432"
    },
    {
        "parkrunning": 2,
        "5k Cancellations": 0,
        "Total": 2,
        "time": "2026-02-12 13:10:13.401488"
    },
    {
        "parkrunning": 2,
        "5k Cancellations": 0,
        "Total": 2,
        "time": "2026-02-13 07:07:43.201715"
    },
    {
        "parkrunning": 1,
        "5k Cancellations": 1,
        "Total": 2,
        "time": "2026-02-13 09:54:48.365169"
    },
    {
        "parkrunning": 1,
        "5k Cancellations": 1,
        "Total": 2,
        "time": "2026-02-13 13:16:24.259765"
    },
    {
        "parkrunning": 2,
        "5k Cancellations": 0,
        "Total": 2,
        "time": "2026-02-13 15:51:29.809369"
    },
    {
        "parkrunning": 2,
        "5k Cancellations": 0,
        "Total": 2,
        "time": "2026-02-13 22:40:33.186103"
    },
    {
        "parkrunning": 1,
        "5k Cancellations": 1,
        "Total": 2,
        "time": "2026-02-13 23:37:40.992548"
    },
    {
        "parkrunning": 2,
        "5k Cancellations": 0,
        "Total": 2,
        "time": "2026-02-14 02:01:01.650509"
    },
    {
        "parkrunning": 2,
        "5k Cancellations": 0,
        "Total": 2,
        "time": "2026-02-14 05:43:48.410925"
    },
    {
        "parkrunning": 1,
        "5k Cancellations": 1,
        "Total": 2,
        "time": "2026-02-14 06:04:44.110571"
    },
    {
        "parkrunning": 1,
        "5k Cancellations": 1,
        "Total": 2,
        "time": "2026-02-14 06:43:46.853949"
    },
    {
        "parkrunning": 2,
        "5k Cancellations": 0,
        "Total": 2,
        "time": "2026-02-14 07:09:46.937624"
    },
    {
        "parkrunning": 2,
        "5k Cancellations": 0,
        "Total": 2,
        "time": "2026-02-14 07:54:03.183932"
    },
    {
        "parkrunning": 1,
        "5k Cancellations": 1,
        "Total": 2,
        "time": "2026-02-14 08:32:30.795946"
    },
    {
        "parkrunning": 2,
        "5k Cancellations": 0,
        "Total": 2,
        "time": "2026-02-14 08:57:05.890587"
    },
    {
        "parkrunning": 2,
        "5k Cancellations": 0,
        "Total": 2,
        "time": "2026-02-14 09:30:40.515986"
    },
    {
        "parkrunning": 1,
        "5k Cancellations": 1,
        "Total": 2,
        "time": "2026-02-14 09:53:57.306942"
    },
    {
        "parkrunning": 2,
        "5k Cancellations": 0,
        "Total": 2,
        "time": "2026-02-14 12:48:23.214187"
    },
    {
        "parkrunning": 2,
        "5k Cancellations": 0,
        "Total": 2,
        "time": "2026-02-14 15:25:54.393728"
    },
    {
        "parkrunning": 1,
        "5k Cancellations": 1,
        "Total": 2,
        "time": "2026-02-14 18:35:02.963199"
    },
    {
        "parkrunning": 2,
        "5k Cancellations": 0,
        "Total": 2,
        "time": "2026-02-14 21:24:40.829328"
    },
    {
        "parkrunning": 2,
        "5k Cancellations": 0,
        "Total": 2,
        "time": "2026-02-15 09:27:02.044302"
    },
    {
        "parkrunning": 1,
        "5k Cancellations": 1,
        "Total": 2,
        "time": "2026-02-15 12:38:02.645159"
    },
    {
        "parkrunning": 2,
        "5k Cancellations": 0,
        "Total": 2,
        "time": "2026-02-15 15:20:22.439351"
    },
    {
        "parkrunning": 1,
        "5k Cancellations": 1,
        "Total": 2,
        "time": "2026-02-15 18:28:06.250404"
    },
    {
        "parkrunning": 2,
        "5k Cancellations": 0,
        "Total": 2,
        "time": "2026-02-15 21:19:17.698536"
    },
    {
        "parkrunning": 2,
        "5k Cancellations": 0,
        "Total": 2,
        "time": "2026-02-16 04:59:54.734446"
    },
    {
        "parkrunning": 1,
        "5k Cancellations": 1,
        "Total": 2,
        "time": "2026-02-16 07:04:21.714538"
    },
    {
        "parkrunning": 1,
        "5k Cancellations": 1,
        "Total": 2,
        "time": "2026-02-16 09:55:29.390605"
    },
    {
        "parkrunning": 2,
        "5k Cancellations": 0,
        "Total": 2,
        "time": "2026-02-16 13:05:34.597105"
    },
    {
        "parkrunning": 2,
        "5k Cancellations": 0,
        "Total": 2,
        "time": "2026-02-16 18:44:28.097676"
    },
    {
        "parkrunning": 1,
        "5k Cancellations": 1,
        "Total": 2,
        "time": "2026-02-16 21:29:29.785451"
    },
    {
        "parkrunning": 2,
        "5k Cancellations": 0,
        "Total": 2,
        "time": "2026-02-17 02:10:02.841060"
    },
    {
        "parkrunning": 2,
        "5k Cancellations": 0,
        "Total": 2,
        "time": "2026-02-17 04:52:44.208739"
    },
    {
        "parkrunning": 1,
        "5k Cancellations": 1,
        "Total": 2,
        "time": "2026-02-17 07:00:16.913742"
    },
    {
        "parkrunning": 2,
        "5k Cancellations": 0,
        "Total": 2,
        "time": "2026-02-17 09:50:51.344480"
    },
    {
        "parkrunning": 2,
        "5k Cancellations": 0,
        "Total": 2,
        "time": "2026-02-17 13:05:30.072797"
    },
    {
        "parkrunning": 1,
        "5k Cancellations": 1,
        "Total": 2,
        "time": "2026-02-17 15:53:26.139676"
    },
    {
        "parkrunning": 1,
        "5k Cancellations": 1,
        "Total": 2,
        "time": "2026-02-17 18:58:33.361752"
    },
    {
        "parkrunning": 2,
        "5k Cancellations": 0,
        "Total": 2,
        "time": "2026-02-17 21:36:49.396428"
    },
    {
        "parkrunning": 1,
        "5k Cancellations": 1,
        "Total": 2,
        "time": "2026-02-18 02:13:24.646040"
    },
    {
        "parkrunning": 2,
        "5k Cancellations": 0,
        "Total": 2,
        "time": "2026-02-18 04:54:20.321465"
    },
    {
        "parkrunning": 2,
        "5k Cancellations": 0,
        "Total": 2,
        "time": "2026-02-18 07:02:49.383908"
    },
    {
        "parkrunning": 1,
        "5k Cancellations": 1,
        "Total": 2,
        "time": "2026-02-18 09:50:10.022591"
    },
    {
        "parkrunning": 2,
        "5k Cancellations": 0,
        "Total": 2,
        "time": "2026-02-18 13:06:14.656784"
    },
    {
        "parkrunning": 1,
        "5k Cancellations": 1,
        "Total": 2,
        "time": "2026-02-18 15:53:02.896369"
    },
    {
        "parkrunning": 2,
        "5k Cancellations": 0,
        "Total": 2,
        "time": "2026-02-18 18:56:20.968789"
    },
    {
        "parkrunning": 2,
        "5k Cancellations": 0,
        "Total": 2,
        "time": "2026-02-19 02:12:39.724841"
    },
    {
        "parkrunning": 1,
        "5k Cancellations": 1,
        "Total": 2,
        "time": "2026-02-19 04:52:58.425964"
    },
    {
        "parkrunning": 2,
        "5k Cancellations": 0,
        "Total": 2,
        "time": "2026-02-19 07:01:33.320914"
    },
    {
        "parkrunning": 2,
        "5k Cancellations": 0,
        "Total": 2,
        "time": "2026-02-19 09:48:13.135198"
    },
    {
        "parkrunning": 1,
        "5k Cancellations": 1,
        "Total": 2,
        "time": "2026-02-19 13:07:28.591842"
    },
    {
        "parkrunning": 2,
        "5k Cancellations": 0,
        "Total": 2,
        "time": "2026-02-19 15:50:26.855965"
    },
    {
        "parkrunning": 2,
        "5k Cancellations": 0,
        "Total": 2,
        "time": "2026-02-20 07:05:33.705544"
    },
    {
        "parkrunning": 1,
        "5k Cancellations": 1,
        "Total": 2,
        "time": "2026-02-20 09:51:08.493622"
    },
    {
        "parkrunning": 1,
        "junior parkrunning": 0,
        "5k Cancellations": 1,
        "junior Cancellations": 0,
        "Total": 2,
        "time": "2026-02-20 15:42:52.500634"
    }
]
