[
    {
        "parkrunning": 2,
        "junior parkrunning": 0,
        "5k Cancellations": 0,
        "junior Cancellations": 0,
        "Total": 2,
        "time": "2025-05-25 21:12:47.385180"
    },
    {
        "parkrunning": 1,
        "5k Cancellations": 1,
        "Total": 2,
        "time": "2025-05-26 01:42:12.752586"
    },
    {
        "parkrunning": 1,
        "junior parkrunning": 0,
        "5k Cancellations": 1,
        "junior Cancellations": 0,
        "Total": 2,
        "time": "2025-05-27 03:43:22.031119"
    }
]
