[
    {
        "parkrunning": 0,
        "junior parkrunning": 0,
        "5k Cancellations": 4,
        "junior Cancellations": 0,
        "Total": 4,
        "time": "2026-01-25 18:22:43.470075"
    },
    {
        "parkrunning": 4,
        "5k Cancellations": 0,
        "Total": 4,
        "time": "2026-01-26 01:58:55.330052"
    },
    {
        "parkrunning": 4,
        "5k Cancellations": 0,
        "Total": 4,
        "time": "2026-01-27 06:37:03.554313"
    },
    {
        "parkrunning": 3,
        "5k Cancellations": 1,
        "Total": 4,
        "time": "2026-01-27 21:18:47.973352"
    },
    {
        "parkrunning": 3,
        "5k Cancellations": 1,
        "Total": 4,
        "time": "2026-01-28 15:33:46.082854"
    },
    {
        "parkrunning": 2,
        "5k Cancellations": 2,
        "Total": 4,
        "time": "2026-01-29 12:59:07.579898"
    },
    {
        "parkrunning": 0,
        "5k Cancellations": 4,
        "Total": 4,
        "time": "2026-01-29 21:28:03.084477"
    },
    {
        "parkrunning": 0,
        "5k Cancellations": 4,
        "Total": 4,
        "time": "2026-02-01 21:17:59.541191"
    },
    {
        "parkrunning": 4,
        "5k Cancellations": 0,
        "Total": 4,
        "time": "2026-02-02 13:01:26.395598"
    },
    {
        "parkrunning": 4,
        "5k Cancellations": 0,
        "Total": 4,
        "time": "2026-02-04 15:42:51.710449"
    },
    {
        "parkrunning": 2,
        "5k Cancellations": 2,
        "Total": 4,
        "time": "2026-02-05 07:00:07.822119"
    },
    {
        "parkrunning": 2,
        "5k Cancellations": 2,
        "Total": 4,
        "time": "2026-02-05 15:41:06.788579"
    },
    {
        "parkrunning": 1,
        "5k Cancellations": 3,
        "Total": 4,
        "time": "2026-02-06 02:41:28.735875"
    },
    {
        "parkrunning": 0,
        "5k Cancellations": 4,
        "Total": 4,
        "time": "2026-02-06 15:49:16.021896"
    },
    {
        "parkrunning": 0,
        "5k Cancellations": 4,
        "Total": 4,
        "time": "2026-02-08 21:21:35.752461"
    },
    {
        "parkrunning": 4,
        "5k Cancellations": 0,
        "Total": 4,
        "time": "2026-02-09 10:03:25.271809"
    },
    {
        "parkrunning": 4,
        "5k Cancellations": 0,
        "Total": 4,
        "time": "2026-02-12 04:58:33.427510"
    },
    {
        "parkrunning": 3,
        "5k Cancellations": 1,
        "Total": 4,
        "time": "2026-02-12 07:02:10.797948"
    },
    {
        "parkrunning": 3,
        "5k Cancellations": 1,
        "Total": 4,
        "time": "2026-02-12 09:51:48.706120"
    },
    {
        "parkrunning": 4,
        "5k Cancellations": 0,
        "Total": 4,
        "time": "2026-02-12 13:10:13.404323"
    },
    {
        "parkrunning": 4,
        "5k Cancellations": 0,
        "Total": 4,
        "time": "2026-02-13 07:07:43.204420"
    },
    {
        "parkrunning": 0,
        "5k Cancellations": 4,
        "Total": 4,
        "time": "2026-02-13 09:54:48.368376"
    },
    {
        "parkrunning": 0,
        "5k Cancellations": 4,
        "Total": 4,
        "time": "2026-02-13 13:16:24.262893"
    },
    {
        "parkrunning": 4,
        "5k Cancellations": 0,
        "Total": 4,
        "time": "2026-02-13 15:51:29.812480"
    },
    {
        "parkrunning": 4,
        "5k Cancellations": 0,
        "Total": 4,
        "time": "2026-02-13 22:40:33.189111"
    },
    {
        "parkrunning": 0,
        "5k Cancellations": 4,
        "Total": 4,
        "time": "2026-02-13 23:37:40.994471"
    },
    {
        "parkrunning": 4,
        "5k Cancellations": 0,
        "Total": 4,
        "time": "2026-02-14 02:01:01.653635"
    },
    {
        "parkrunning": 4,
        "5k Cancellations": 0,
        "Total": 4,
        "time": "2026-02-14 05:43:48.414134"
    },
    {
        "parkrunning": 0,
        "5k Cancellations": 4,
        "Total": 4,
        "time": "2026-02-14 06:04:44.114631"
    },
    {
        "parkrunning": 0,
        "5k Cancellations": 4,
        "Total": 4,
        "time": "2026-02-14 06:43:46.856788"
    },
    {
        "parkrunning": 4,
        "5k Cancellations": 0,
        "Total": 4,
        "time": "2026-02-14 07:09:46.941202"
    },
    {
        "parkrunning": 4,
        "5k Cancellations": 0,
        "Total": 4,
        "time": "2026-02-14 07:54:03.187224"
    },
    {
        "parkrunning": 0,
        "5k Cancellations": 4,
        "Total": 4,
        "time": "2026-02-14 08:32:30.799851"
    },
    {
        "parkrunning": 4,
        "5k Cancellations": 0,
        "Total": 4,
        "time": "2026-02-14 08:57:05.893952"
    },
    {
        "parkrunning": 4,
        "5k Cancellations": 0,
        "Total": 4,
        "time": "2026-02-14 09:30:40.518882"
    },
    {
        "parkrunning": 0,
        "5k Cancellations": 4,
        "Total": 4,
        "time": "2026-02-14 09:53:57.311360"
    },
    {
        "parkrunning": 4,
        "5k Cancellations": 0,
        "Total": 4,
        "time": "2026-02-14 12:48:23.217668"
    },
    {
        "parkrunning": 4,
        "5k Cancellations": 0,
        "Total": 4,
        "time": "2026-02-14 15:25:54.396719"
    },
    {
        "parkrunning": 0,
        "5k Cancellations": 4,
        "Total": 4,
        "time": "2026-02-14 18:35:02.966789"
    },
    {
        "parkrunning": 4,
        "5k Cancellations": 0,
        "Total": 4,
        "time": "2026-02-14 21:24:40.831405"
    },
    {
        "parkrunning": 4,
        "5k Cancellations": 0,
        "Total": 4,
        "time": "2026-02-15 09:27:02.048227"
    },
    {
        "parkrunning": 0,
        "5k Cancellations": 4,
        "Total": 4,
        "time": "2026-02-15 12:38:02.648393"
    },
    {
        "parkrunning": 4,
        "5k Cancellations": 0,
        "Total": 4,
        "time": "2026-02-15 15:20:22.441695"
    },
    {
        "parkrunning": 0,
        "5k Cancellations": 4,
        "Total": 4,
        "time": "2026-02-15 18:28:06.253433"
    },
    {
        "parkrunning": 4,
        "5k Cancellations": 0,
        "Total": 4,
        "time": "2026-02-15 21:19:17.702089"
    },
    {
        "parkrunning": 4,
        "junior parkrunning": 0,
        "5k Cancellations": 0,
        "junior Cancellations": 0,
        "Total": 4,
        "time": "2026-02-19 02:12:39.728469"
    }
]
