[
    {
        "parkrunning": 1,
        "junior parkrunning": 0,
        "5k Cancellations": 0,
        "junior Cancellations": 0,
        "Total": 1,
        "time": "2023-04-16 21:08:24.257634"
    },
    {
        "parkrunning": 1,
        "Total": 1,
        "time": "2023-04-17 06:18:39.305858"
    },
    {
        "parkrunning": 2,
        "Total": 2,
        "time": "2023-04-17 09:14:58.210144"
    },
    {
        "parkrunning": 2,
        "Total": 2,
        "time": "2023-04-18 03:14:39.575019"
    },
    {
        "parkrunning": 1,
        "Total": 1,
        "time": "2023-04-18 06:18:47.225475"
    },
    {
        "parkrunning": 1,
        "junior parkrunning": 0,
        "5k Cancellations": 0,
        "junior Cancellations": 0,
        "Total": 1,
        "time": "2023-04-21 09:17:38.097738"
    }
]
