[
    {
        "parkrunning": 3,
        "junior parkrunning": 0,
        "5k Cancellations": 0,
        "junior Cancellations": 0,
        "Total": 3,
        "time": "2025-03-02 21:12:11.309111"
    },
    {
        "parkrunning": 3,
        "5k Cancellations": 0,
        "Total": 3,
        "time": "2025-03-09 05:10:51.190113"
    },
    {
        "parkrunning": 2,
        "5k Cancellations": 1,
        "Total": 3,
        "time": "2025-03-09 06:14:42.053139"
    },
    {
        "parkrunning": 2,
        "junior parkrunning": 0,
        "5k Cancellations": 1,
        "junior Cancellations": 0,
        "Total": 3,
        "time": "2025-03-09 18:13:30.806391"
    }
]
