[
    {
        "parkrunning": 3,
        "junior parkrunning": 0,
        "5k Cancellations": 0,
        "junior Cancellations": 0,
        "Total": 3,
        "time": "2024-01-07 21:08:46.415695"
    },
    {
        "parkrunning": 3,
        "5k Cancellations": 0,
        "Total": 3,
        "time": "2024-01-12 01:20:07.977307"
    },
    {
        "parkrunning": 2,
        "5k Cancellations": 1,
        "Total": 3,
        "time": "2024-01-12 03:19:04.864731"
    },
    {
        "parkrunning": 2,
        "junior parkrunning": 0,
        "5k Cancellations": 1,
        "junior Cancellations": 0,
        "Total": 3,
        "time": "2024-01-12 18:22:56.862081"
    }
]
