[
    {
        "parkrunning": 1,
        "junior parkrunning": 0,
        "5k Cancellations": 3,
        "junior Cancellations": 0,
        "Total": 4,
        "time": "2026-01-25 18:22:43.474272"
    },
    {
        "parkrunning": 4,
        "5k Cancellations": 0,
        "Total": 4,
        "time": "2026-01-26 01:58:55.333999"
    },
    {
        "parkrunning": 4,
        "5k Cancellations": 0,
        "Total": 4,
        "time": "2026-01-27 21:18:47.977491"
    },
    {
        "parkrunning": 3,
        "5k Cancellations": 1,
        "Total": 4,
        "time": "2026-01-28 15:33:46.085490"
    },
    {
        "parkrunning": 3,
        "5k Cancellations": 1,
        "Total": 4,
        "time": "2026-01-30 09:55:51.429335"
    },
    {
        "parkrunning": 1,
        "5k Cancellations": 3,
        "Total": 4,
        "time": "2026-01-30 21:34:10.501886"
    },
    {
        "parkrunning": 1,
        "5k Cancellations": 3,
        "Total": 4,
        "time": "2026-02-01 21:17:59.544354"
    },
    {
        "parkrunning": 4,
        "5k Cancellations": 0,
        "Total": 4,
        "time": "2026-02-02 13:01:26.399397"
    },
    {
        "parkrunning": 4,
        "5k Cancellations": 0,
        "Total": 4,
        "time": "2026-02-05 15:41:06.791696"
    },
    {
        "parkrunning": 3,
        "5k Cancellations": 1,
        "Total": 4,
        "time": "2026-02-06 02:41:28.739477"
    },
    {
        "parkrunning": 3,
        "5k Cancellations": 1,
        "Total": 4,
        "time": "2026-02-06 15:49:16.025392"
    },
    {
        "parkrunning": 1,
        "5k Cancellations": 3,
        "Total": 4,
        "time": "2026-02-06 19:44:29.726527"
    },
    {
        "parkrunning": 1,
        "5k Cancellations": 3,
        "Total": 4,
        "time": "2026-02-08 21:21:35.756235"
    },
    {
        "parkrunning": 4,
        "5k Cancellations": 0,
        "Total": 4,
        "time": "2026-02-09 10:03:25.275917"
    },
    {
        "parkrunning": 4,
        "5k Cancellations": 0,
        "Total": 4,
        "time": "2026-02-13 07:07:43.209165"
    },
    {
        "parkrunning": 3,
        "5k Cancellations": 1,
        "Total": 4,
        "time": "2026-02-13 09:54:48.373256"
    },
    {
        "parkrunning": 3,
        "5k Cancellations": 1,
        "Total": 4,
        "time": "2026-02-13 13:16:24.267007"
    },
    {
        "parkrunning": 4,
        "5k Cancellations": 0,
        "Total": 4,
        "time": "2026-02-13 15:51:29.817860"
    },
    {
        "parkrunning": 4,
        "5k Cancellations": 0,
        "Total": 4,
        "time": "2026-02-13 22:40:33.193038"
    },
    {
        "parkrunning": 3,
        "5k Cancellations": 1,
        "Total": 4,
        "time": "2026-02-13 23:37:40.998281"
    },
    {
        "parkrunning": 4,
        "5k Cancellations": 0,
        "Total": 4,
        "time": "2026-02-14 02:01:01.658847"
    },
    {
        "parkrunning": 4,
        "5k Cancellations": 0,
        "Total": 4,
        "time": "2026-02-14 05:43:48.418469"
    },
    {
        "parkrunning": 3,
        "5k Cancellations": 1,
        "Total": 4,
        "time": "2026-02-14 06:04:44.120049"
    },
    {
        "parkrunning": 3,
        "5k Cancellations": 1,
        "Total": 4,
        "time": "2026-02-14 06:43:46.860632"
    },
    {
        "parkrunning": 4,
        "5k Cancellations": 0,
        "Total": 4,
        "time": "2026-02-14 07:09:46.946063"
    },
    {
        "parkrunning": 4,
        "5k Cancellations": 0,
        "Total": 4,
        "time": "2026-02-14 07:54:03.192921"
    },
    {
        "parkrunning": 3,
        "5k Cancellations": 1,
        "Total": 4,
        "time": "2026-02-14 08:32:30.805085"
    },
    {
        "parkrunning": 4,
        "5k Cancellations": 0,
        "Total": 4,
        "time": "2026-02-14 08:57:05.899595"
    },
    {
        "parkrunning": 4,
        "5k Cancellations": 0,
        "Total": 4,
        "time": "2026-02-14 09:30:40.523405"
    },
    {
        "parkrunning": 3,
        "5k Cancellations": 1,
        "Total": 4,
        "time": "2026-02-14 09:53:57.316435"
    },
    {
        "parkrunning": 4,
        "5k Cancellations": 0,
        "Total": 4,
        "time": "2026-02-14 12:48:23.222379"
    },
    {
        "parkrunning": 4,
        "5k Cancellations": 0,
        "Total": 4,
        "time": "2026-02-14 15:25:54.401998"
    },
    {
        "parkrunning": 2,
        "5k Cancellations": 2,
        "Total": 4,
        "time": "2026-02-14 18:35:02.971190"
    },
    {
        "parkrunning": 4,
        "5k Cancellations": 0,
        "Total": 4,
        "time": "2026-02-14 21:24:40.834662"
    },
    {
        "parkrunning": 4,
        "5k Cancellations": 0,
        "Total": 4,
        "time": "2026-02-15 09:27:02.054372"
    },
    {
        "parkrunning": 2,
        "5k Cancellations": 2,
        "Total": 4,
        "time": "2026-02-15 12:38:02.653315"
    },
    {
        "parkrunning": 4,
        "5k Cancellations": 0,
        "Total": 4,
        "time": "2026-02-15 15:20:22.446707"
    },
    {
        "parkrunning": 2,
        "5k Cancellations": 2,
        "Total": 4,
        "time": "2026-02-15 18:28:06.259063"
    },
    {
        "parkrunning": 4,
        "5k Cancellations": 0,
        "Total": 4,
        "time": "2026-02-15 21:19:17.706771"
    },
    {
        "parkrunning": 4,
        "5k Cancellations": 0,
        "Total": 4,
        "time": "2026-02-21 15:25:08.353049"
    },
    {
        "parkrunning": 3,
        "5k Cancellations": 1,
        "Total": 4,
        "time": "2026-02-21 18:34:58.211513"
    },
    {
        "parkrunning": 3,
        "5k Cancellations": 1,
        "Total": 4,
        "time": "2026-02-21 21:23:07.650553"
    },
    {
        "parkrunning": 4,
        "5k Cancellations": 0,
        "Total": 4,
        "time": "2026-02-22 01:44:46.215821"
    },
    {
        "parkrunning": 4,
        "5k Cancellations": 0,
        "Total": 4,
        "time": "2026-02-22 04:45:48.437794"
    },
    {
        "parkrunning": 3,
        "5k Cancellations": 1,
        "Total": 4,
        "time": "2026-02-22 05:46:50.735528"
    },
    {
        "parkrunning": 4,
        "5k Cancellations": 0,
        "Total": 4,
        "time": "2026-02-22 06:40:26.384766"
    },
    {
        "parkrunning": 4,
        "5k Cancellations": 0,
        "Total": 4,
        "time": "2026-02-22 09:25:33.877659"
    },
    {
        "parkrunning": 3,
        "5k Cancellations": 1,
        "Total": 4,
        "time": "2026-02-22 12:37:30.274324"
    },
    {
        "parkrunning": 4,
        "5k Cancellations": 0,
        "Total": 4,
        "time": "2026-02-22 15:20:17.519233"
    },
    {
        "parkrunning": 4,
        "junior parkrunning": 0,
        "5k Cancellations": 0,
        "junior Cancellations": 0,
        "Total": 4,
        "time": "2026-02-28 18:33:12.755186"
    }
]
