[
    {
        "parkrunning": 2,
        "junior parkrunning": 0,
        "5k Cancellations": 0,
        "junior Cancellations": 0,
        "Total": 2,
        "time": "2025-12-28 18:22:15.976056"
    },
    {
        "parkrunning": 2,
        "5k Cancellations": 0,
        "Total": 2,
        "time": "2026-01-23 18:43:46.916981"
    },
    {
        "parkrunning": 1,
        "5k Cancellations": 1,
        "Total": 2,
        "time": "2026-01-24 03:26:40.874243"
    },
    {
        "parkrunning": 1,
        "junior parkrunning": 0,
        "5k Cancellations": 1,
        "junior Cancellations": 0,
        "Total": 2,
        "time": "2026-01-25 05:24:38.469238"
    }
]
