[
    {
        "parkrunning": 356,
        "junior parkrunning": 225,
        "5k Cancellations": 216,
        "junior Cancellations": 72,
        "Total": 869,
        "time": "2021-11-28 21:08:34.102102"
    },
    {
        "parkrunning": 556,
        "junior parkrunning": 274,
        "5k Cancellations": 16,
        "junior Cancellations": 23,
        "Total": 869,
        "time": "2021-11-29 00:51:36.023169"
    },
    {
        "parkrunning": 556,
        "5k Cancellations": 16,
        "Total": 869,
        "time": "2021-11-29 15:16:46.825185"
    },
    {
        "parkrunning": 555,
        "5k Cancellations": 17,
        "Total": 869,
        "time": "2021-11-29 18:21:03.418409"
    },
    {
        "parkrunning": 555,
        "5k Cancellations": 17,
        "Total": 869,
        "time": "2021-11-30 18:18:23.413619"
    },
    {
        "parkrunning": 554,
        "5k Cancellations": 18,
        "Total": 869,
        "time": "2021-11-30 21:13:46.569996"
    },
    {
        "parkrunning": 554,
        "junior parkrunning": 274,
        "5k Cancellations": 18,
        "junior Cancellations": 23,
        "Total": 869,
        "time": "2021-12-01 03:16:16.904934"
    }
]
