[
    {
        "parkrunning": 624,
        "junior parkrunning": 359,
        "5k Cancellations": 14,
        "junior Cancellations": 22,
        "Total": 1019,
        "time": "2024-11-10 21:10:56.602092"
    },
    {
        "parkrunning": 628,
        "junior parkrunning": 376,
        "5k Cancellations": 10,
        "junior Cancellations": 5,
        "Total": 1019,
        "time": "2024-11-11 01:19:03.181149"
    },
    {
        "parkrunning": 628,
        "junior parkrunning": 376,
        "5k Cancellations": 10,
        "junior Cancellations": 5,
        "Total": 1019,
        "time": "2024-11-11 18:22:40.288641"
    }
]
