[
    {
        "parkrunning": 573,
        "junior parkrunning": 290,
        "5k Cancellations": 12,
        "junior Cancellations": 10,
        "Total": 885,
        "time": "2022-04-24 21:10:17.358954"
    },
    {
        "parkrunning": 578,
        "junior parkrunning": 293,
        "5k Cancellations": 7,
        "junior Cancellations": 7,
        "Total": 885,
        "time": "2022-04-25 01:19:49.961041"
    },
    {
        "junior parkrunning": 293,
        "junior Cancellations": 7,
        "Total": 885,
        "time": "2022-04-25 12:30:49.530612"
    },
    {
        "junior parkrunning": 292,
        "junior Cancellations": 8,
        "Total": 885,
        "time": "2022-04-25 15:19:43.596039"
    },
    {
        "parkrunning": 578,
        "5k Cancellations": 7,
        "Total": 885,
        "time": "2022-04-25 18:23:02.532406"
    },
    {
        "parkrunning": 577,
        "5k Cancellations": 8,
        "Total": 885,
        "time": "2022-04-25 21:13:55.533423"
    },
    {
        "parkrunning": 577,
        "5k Cancellations": 8,
        "Total": 885,
        "time": "2022-04-26 12:34:00.187184"
    },
    {
        "parkrunning": 576,
        "5k Cancellations": 9,
        "Total": 885,
        "time": "2022-04-26 15:18:24.146121"
    },
    {
        "parkrunning": 576,
        "junior parkrunning": 292,
        "5k Cancellations": 9,
        "junior Cancellations": 8,
        "Total": 885,
        "time": "2022-04-27 06:21:49.647331"
    }
]
