[
    {
        "parkrunning": 6,
        "junior parkrunning": 7,
        "5k Cancellations": 33,
        "junior Cancellations": 13,
        "Total": 59,
        "time": "2025-01-26 21:11:12.133416"
    },
    {
        "parkrunning": 39,
        "junior parkrunning": 20,
        "5k Cancellations": 0,
        "junior Cancellations": 0,
        "Total": 59,
        "time": "2025-01-27 01:18:26.124907"
    },
    {
        "parkrunning": 39,
        "5k Cancellations": 0,
        "Total": 59,
        "time": "2025-01-29 01:16:55.790650"
    },
    {
        "parkrunning": 38,
        "5k Cancellations": 1,
        "Total": 59,
        "time": "2025-01-29 03:18:41.393092"
    },
    {
        "parkrunning": 38,
        "5k Cancellations": 1,
        "Total": 59,
        "time": "2025-01-30 12:33:31.861352"
    },
    {
        "parkrunning": 37,
        "5k Cancellations": 2,
        "Total": 59,
        "time": "2025-01-30 15:18:07.206773"
    },
    {
        "parkrunning": 37,
        "5k Cancellations": 2,
        "Total": 59,
        "time": "2025-01-30 21:15:37.187695"
    },
    {
        "parkrunning": 36,
        "5k Cancellations": 3,
        "Total": 59,
        "time": "2025-01-31 01:42:10.897479"
    },
    {
        "junior parkrunning": 20,
        "junior Cancellations": 0,
        "Total": 59,
        "time": "2025-01-31 06:30:40.277245"
    },
    {
        "junior parkrunning": 19,
        "junior Cancellations": 1,
        "Total": 59,
        "time": "2025-01-31 09:22:29.999227"
    },
    {
        "parkrunning": 36,
        "5k Cancellations": 3,
        "Total": 59,
        "time": "2025-01-31 12:41:24.273553"
    },
    {
        "parkrunning": 35,
        "5k Cancellations": 4,
        "Total": 59,
        "time": "2025-01-31 15:20:07.087292"
    },
    {
        "parkrunning": 34,
        "5k Cancellations": 5,
        "Total": 59,
        "time": "2025-01-31 18:31:08.843730"
    },
    {
        "junior parkrunning": 19,
        "junior Cancellations": 1,
        "Total": 59,
        "time": "2025-01-31 23:19:42.076108"
    },
    {
        "junior parkrunning": 18,
        "junior Cancellations": 2,
        "Total": 59,
        "time": "2025-02-01 01:18:17.221026"
    },
    {
        "junior parkrunning": 18,
        "junior Cancellations": 2,
        "Total": 59,
        "time": "2025-02-01 08:38:23.668494"
    },
    {
        "junior parkrunning": 17,
        "junior Cancellations": 3,
        "Total": 59,
        "time": "2025-02-01 09:16:12.834490"
    },
    {
        "parkrunning": 34,
        "5k Cancellations": 5,
        "Total": 59,
        "time": "2025-02-01 09:36:35.788958"
    },
    {
        "parkrunning": 33,
        "junior parkrunning": 17,
        "5k Cancellations": 6,
        "junior Cancellations": 3,
        "Total": 59,
        "time": "2025-02-01 12:28:40.227692"
    },
    {
        "parkrunning": 33,
        "junior parkrunning": 16,
        "5k Cancellations": 6,
        "junior Cancellations": 4,
        "Total": 59,
        "time": "2025-02-01 15:17:08.731029"
    }
]
