[
    {
        "parkrunning": 74,
        "junior parkrunning": 33,
        "5k Cancellations": 5,
        "junior Cancellations": 5,
        "Total": 117,
        "time": "2026-01-25 18:22:43.463134"
    },
    {
        "parkrunning": 78,
        "junior parkrunning": 37,
        "5k Cancellations": 1,
        "junior Cancellations": 1,
        "Total": 117,
        "time": "2026-01-26 01:58:55.324029"
    },
    {
        "parkrunning": 78,
        "5k Cancellations": 1,
        "Total": 117,
        "time": "2026-01-28 15:33:46.078527"
    },
    {
        "parkrunning": 77,
        "5k Cancellations": 2,
        "Total": 117,
        "time": "2026-01-29 12:59:07.574687"
    },
    {
        "parkrunning": 76,
        "5k Cancellations": 3,
        "Total": 117,
        "time": "2026-01-29 21:28:03.079577"
    },
    {
        "parkrunning": 76,
        "5k Cancellations": 3,
        "Total": 117,
        "time": "2026-01-30 09:55:51.420146"
    },
    {
        "parkrunning": 75,
        "5k Cancellations": 4,
        "Total": 117,
        "time": "2026-01-30 21:34:10.494244"
    },
    {
        "parkrunning": 75,
        "5k Cancellations": 4,
        "Total": 117,
        "time": "2026-01-31 08:54:10.035112"
    },
    {
        "parkrunning": 74,
        "junior parkrunning": 37,
        "5k Cancellations": 5,
        "junior Cancellations": 1,
        "Total": 117,
        "time": "2026-01-31 09:50:59.684969"
    },
    {
        "junior parkrunning": 35,
        "junior Cancellations": 3,
        "Total": 117,
        "time": "2026-02-01 01:52:17.988823"
    },
    {
        "parkrunning": 74,
        "junior parkrunning": 35,
        "5k Cancellations": 5,
        "junior Cancellations": 3,
        "Total": 117,
        "time": "2026-02-01 06:51:42.784700"
    }
]
