[
    {
        "parkrunning": 63,
        "junior parkrunning": 26,
        "5k Cancellations": 1,
        "junior Cancellations": 1,
        "Total": 91,
        "time": "2022-08-14 21:10:48.595229"
    },
    {
        "junior parkrunning": 25,
        "junior Cancellations": 2,
        "Total": 91,
        "time": "2022-08-15 01:51:29.398123"
    },
    {
        "junior parkrunning": 25,
        "Total": 91,
        "time": "2022-08-19 21:20:20.574975"
    },
    {
        "junior parkrunning": 26,
        "Total": 92,
        "time": "2022-08-19 22:25:14.641868"
    },
    {
        "parkrunning": 63,
        "junior parkrunning": 26,
        "5k Cancellations": 1,
        "junior Cancellations": 2,
        "Total": 92,
        "time": "2022-08-21 01:04:14.965455"
    }
]
