[
    {
        "parkrunning": 73,
        "junior parkrunning": 31,
        "5k Cancellations": 2,
        "junior Cancellations": 4,
        "Total": 110,
        "time": "2025-06-08 21:12:53.185786"
    },
    {
        "parkrunning": 72,
        "junior parkrunning": 33,
        "5k Cancellations": 3,
        "junior Cancellations": 2,
        "Total": 110,
        "time": "2025-06-09 01:46:34.016097"
    },
    {
        "parkrunning": 72,
        "5k Cancellations": 3,
        "Total": 110,
        "time": "2025-06-13 19:20:20.900601"
    },
    {
        "parkrunning": 71,
        "5k Cancellations": 4,
        "Total": 110,
        "time": "2025-06-13 20:28:09.219630"
    },
    {
        "parkrunning": 71,
        "Total": 110,
        "time": "2025-06-13 21:23:39.110065"
    },
    {
        "parkrunning": 72,
        "Total": 111,
        "time": "2025-06-13 22:24:30.052341"
    },
    {
        "parkrunning": 72,
        "junior parkrunning": 33,
        "5k Cancellations": 4,
        "junior Cancellations": 2,
        "Total": 111,
        "time": "2025-06-14 21:16:54.205610"
    }
]
