[
    {
        "parkrunning": 51,
        "junior parkrunning": 20,
        "5k Cancellations": 0,
        "junior Cancellations": 0,
        "Total": 71,
        "time": "2024-02-18 21:08:17.361409"
    },
    {
        "junior parkrunning": 18,
        "junior Cancellations": 2,
        "Total": 71,
        "time": "2024-02-19 01:00:24.797724"
    },
    {
        "parkrunning": 51,
        "junior parkrunning": 18,
        "5k Cancellations": 0,
        "junior Cancellations": 2,
        "Total": 71,
        "time": "2024-02-19 21:12:55.319787"
    }
]
