[
    {
        "parkrunning": 41,
        "junior parkrunning": 14,
        "5k Cancellations": 3,
        "junior Cancellations": 4,
        "Total": 62,
        "time": "2021-10-24 21:08:33.443992"
    },
    {
        "parkrunning": 42,
        "junior parkrunning": 18,
        "5k Cancellations": 2,
        "junior Cancellations": 0,
        "Total": 62,
        "time": "2021-10-25 00:53:40.553949"
    },
    {
        "parkrunning": 42,
        "5k Cancellations": 2,
        "Total": 62,
        "time": "2021-10-29 15:21:59.585657"
    },
    {
        "parkrunning": 41,
        "5k Cancellations": 3,
        "Total": 62,
        "time": "2021-10-29 18:24:36.646768"
    },
    {
        "parkrunning": 41,
        "junior parkrunning": 18,
        "5k Cancellations": 3,
        "junior Cancellations": 0,
        "Total": 62,
        "time": "2021-10-30 05:12:30.537573"
    }
]
