[
    {
        "parkrunning": 53,
        "junior parkrunning": 24,
        "5k Cancellations": 1,
        "junior Cancellations": 1,
        "Total": 79,
        "time": "2025-01-19 21:10:55.136106"
    },
    {
        "parkrunning": 54,
        "5k Cancellations": 0,
        "Total": 79,
        "time": "2025-01-20 01:18:17.107002"
    },
    {
        "parkrunning": 54,
        "5k Cancellations": 0,
        "Total": 79,
        "time": "2025-01-22 15:18:17.115712"
    },
    {
        "parkrunning": 53,
        "5k Cancellations": 1,
        "Total": 79,
        "time": "2025-01-22 18:24:15.507577"
    },
    {
        "junior parkrunning": 24,
        "junior Cancellations": 1,
        "Total": 79,
        "time": "2025-01-23 09:18:14.506243"
    },
    {
        "junior parkrunning": 23,
        "junior Cancellations": 2,
        "Total": 79,
        "time": "2025-01-23 12:34:35.840044"
    },
    {
        "parkrunning": 53,
        "5k Cancellations": 1,
        "Total": 79,
        "time": "2025-01-23 15:18:16.582425"
    },
    {
        "parkrunning": 52,
        "5k Cancellations": 2,
        "Total": 79,
        "time": "2025-01-23 18:23:36.180983"
    },
    {
        "parkrunning": 52,
        "5k Cancellations": 2,
        "Total": 79,
        "time": "2025-01-24 20:22:29.454177"
    },
    {
        "parkrunning": 51,
        "junior parkrunning": 23,
        "5k Cancellations": 3,
        "junior Cancellations": 2,
        "Total": 79,
        "time": "2025-01-24 21:19:22.572892"
    }
]
