[
    {
        "parkrunning": 56,
        "junior parkrunning": 15,
        "5k Cancellations": 3,
        "junior Cancellations": 5,
        "Total": 79,
        "time": "2021-08-23 15:35:54.061470"
    },
    {
        "parkrunning": 56,
        "junior parkrunning": 15,
        "5k Cancellations": 3,
        "junior Cancellations": 5,
        "Total": 79,
        "time": "2021-08-23 15:57:46.557583"
    },
    {
        "parkrunning": 56,
        "junior parkrunning": 15,
        "5k Cancellations": 3,
        "junior Cancellations": 5,
        "Total": 79,
        "time": "2021-08-23 17:00:59.938934"
    },
    {
        "parkrunning": 56,
        "junior parkrunning": 15,
        "5k Cancellations": 3,
        "junior Cancellations": 5,
        "Total": 79,
        "time": "2021-08-23 17:12:54.873473"
    },
    {
        "parkrunning": 56,
        "junior parkrunning": 15,
        "5k Cancellations": 3,
        "junior Cancellations": 5,
        "Total": 79,
        "time": "2021-08-23 17:31:20.138589"
    },
    {
        "parkrunning": 56,
        "junior parkrunning": 15,
        "5k Cancellations": 3,
        "junior Cancellations": 5,
        "Total": 79,
        "time": "2021-08-23 18:19:06.867498"
    },
    {
        "parkrunning": 56,
        "junior parkrunning": 15,
        "5k Cancellations": 3,
        "junior Cancellations": 5,
        "Total": 79,
        "time": "2021-08-23 21:12:34.938350"
    },
    {
        "parkrunning": 56,
        "junior parkrunning": 15,
        "5k Cancellations": 3,
        "junior Cancellations": 5,
        "Total": 79,
        "time": "2021-08-24 00:45:22.234384"
    },
    {
        "parkrunning": 56,
        "junior parkrunning": 15,
        "5k Cancellations": 3,
        "junior Cancellations": 5,
        "Total": 79,
        "time": "2021-08-24 03:15:35.126218"
    },
    {
        "parkrunning": 56,
        "junior parkrunning": 15,
        "5k Cancellations": 3,
        "junior Cancellations": 5,
        "Total": 79,
        "time": "2021-08-24 06:17:35.092918"
    }
]